setup.py
haber_devops.egg-info/PKG-INFO
haber_devops.egg-info/SOURCES.txt
haber_devops.egg-info/dependency_links.txt
haber_devops.egg-info/entry_points.txt
haber_devops.egg-info/requires.txt
haber_devops.egg-info/top_level.txt
haberdevops/__init__.py
haberdevops/aws_configure.py
haberdevops/config.py
haberdevops/deploy.py
haberdevops/deploy_algorithm.py
haberdevops/docker.py
haberdevops/ec2.py
haberdevops/ecr.py
haberdevops/main.py
haberdevops/populate_instances.py
haberdevops/rds.py
haberdevops/route53.py
haberdevops/s3.py
haberdevops/ssh.py
haberdevops/tags.py